.gitignore
AUTHORS
LICENSE
README.md
setup.py
wallaby/__init__.py
wallaby/backends/__init__.py
wallaby/backends/http/__init__.py
wallaby_backend_http.egg-info/PKG-INFO
wallaby_backend_http.egg-info/SOURCES.txt
wallaby_backend_http.egg-info/dependency_links.txt
wallaby_backend_http.egg-info/requires.txt
wallaby_backend_http.egg-info/top_level.txt