Metadata-Version: 1.0
Name: wallaby-backend-http
Version: 0.1
Summary: Wallaby backend for http(s).
Home-page: https://github.com/FreshXOpenSource/wallaby-backend-http
Author: FreshX GbR
Author-email: wallaby@freshx.de
License: BSD
Platform: UNKNOWN
